dsd_pythonanywhere/__init__.py
dsd_pythonanywhere/client.py
dsd_pythonanywhere/deploy.py
dsd_pythonanywhere/deploy_messages.py
dsd_pythonanywhere/platform_deployer.py
dsd_pythonanywhere/plugin_config.py
dsd_pythonanywhere/templates/settings.py
dsd_pythonanywhere/templates/wsgi.py
dsd_pythonanywhere-0.1.0.dist-info/METADATA
dsd_pythonanywhere-0.1.0.dist-info/WHEEL
dsd_pythonanywhere-0.1.0.dist-info/RECORD
