Metadata-Version: 2.4
Name: dsd-pythonanywhere
Version: 0.1.0
Summary: A plugin for django-simple-deploy, supporting deployments to PythonAnywhere.
Project-URL: Homepage, https://github.com/caktus/dsd-pythonanywhere
Project-URL: Source, https://github.com/caktus/dsd-pythonanywhere
Project-URL: Tracker, https://github.com/caktus/dsd-pythonanywhere/issues
Author-email: Caktus Consulting Group <solutions@caktusgroup.com>
License-Expression: BSD-3-Clause
Keywords: deployment,django,pythonanywhere,simple-deploy
Classifier: Development Status :: 4 - Beta
Classifier: Framework :: Django
Classifier: Framework :: Django :: 4.2
Classifier: Framework :: Django :: 5.0
Classifier: Framework :: Django :: 5.1
Classifier: Framework :: Django :: 5.2
Classifier: Framework :: Django :: 6.0
Classifier: Intended Audience :: Developers
Classifier: License :: OSI Approved :: BSD License
Classifier: Operating System :: OS Independent
Classifier: Programming Language :: Python :: 3
Classifier: Programming Language :: Python :: 3 :: Only
Classifier: Programming Language :: Python :: 3.10
Classifier: Programming Language :: Python :: 3.11
Classifier: Programming Language :: Python :: 3.12
Classifier: Programming Language :: Python :: 3.13
Classifier: Programming Language :: Python :: 3.14
Classifier: Topic :: Software Development :: Build Tools
Classifier: Topic :: System :: Software Distribution
Requires-Python: >=3.10
Requires-Dist: django-simple-deploy>=0.9.0
Requires-Dist: django>=4.2
Requires-Dist: pluggy>=1.5.0
Requires-Dist: pythonanywhere-core>=0.2.4
Requires-Dist: pythonanywhere>=0.15.5
Requires-Dist: requests>=2.32.2
Requires-Dist: tomli>=2.0.1; python_version < '3.11'
